{"nodes":[{"name":"cellulose","group":5},{"name":"cellulosic ethanol","group":19},{"name":"ethanol","group":19},{"name":"paper","group":16},{"name":"sugar","group":14},{"name":"wood","group":16}],"links":[{"source":0,"target":1,"value":1.0},{"source":0,"target":2,"value":1.0},{"source":1,"target":0,"value":1.0},{"source":1,"target":3,"value":1.0},{"source":1,"target":4,"value":1.0},{"source":1,"target":5,"value":1.0},{"source":2,"target":0,"value":1.0},{"source":2,"target":3,"value":1.0},{"source":2,"target":4,"value":1.0},{"source":2,"target":5,"value":1.0},{"source":3,"target":1,"value":1.0},{"source":3,"target":2,"value":1.0},{"source":4,"target":1,"value":1.0},{"source":4,"target":2,"value":1.0},{"source":5,"target":1,"value":1.0},{"source":5,"target":2,"value":1.0}]}